LICENSE
MANIFEST.in
README.md
setup.cfg
setup.py
examples/__init__.py
examples/acs2/__init__.py
examples/acs2/boolean_multiplexer/__init__.py
examples/acs2/boolean_multiplexer/acs2_in_multiplexer.py
examples/acs2/boolean_multiplexer/perform_experiment.py
examples/acs2/boolean_multiplexer/utils.py
examples/acs2/handeye/__init__.py
examples/acs2/handeye/acs2_in_handeye_ap.py
examples/acs2/handeye/acs2_in_handeye_no_ap.py
examples/acs2/handeye/utils.py
examples/acs2/maze/__init__.py
examples/acs2/maze/acs2_in_maze.py
examples/acs2/maze/utils.py
examples/acs2/taxi/TaxiAdapter.py
examples/acs2/taxi/__init__.py
examples/acs2/taxi/acs2_in_taxi.py
examples/racs/__init__.py
examples/racs/checkerboard/__init__.py
examples/racs/checkerboard/racs_in_checkberboard.py
examples/racs/rmpx/__init__.py
examples/racs/rmpx/racs_in_rmpx.py
lcs/Perception.py
lcs/TypedList.py
lcs/__init__.py
lcs/metrics.py
lcs/utils.py
lcs/agents/Agent.py
lcs/agents/EnvironmentAdapter.py
lcs/agents/PerceptionString.py
lcs/agents/__init__.py
lcs/agents/acs2/ACS2.py
lcs/agents/acs2/Classifier.py
lcs/agents/acs2/ClassifiersList.py
lcs/agents/acs2/Condition.py
lcs/agents/acs2/Configuration.py
lcs/agents/acs2/Effect.py
lcs/agents/acs2/PMark.py
lcs/agents/acs2/__init__.py
lcs/agents/acs2/components/__init__.py
lcs/agents/acs2/components/alp.py
lcs/agents/racs/Classifier.py
lcs/agents/racs/ClassifierList.py
lcs/agents/racs/Condition.py
lcs/agents/racs/Configuration.py
lcs/agents/racs/Effect.py
lcs/agents/racs/Mark.py
lcs/agents/racs/RACS.py
lcs/agents/racs/__init__.py
lcs/agents/racs/metrics.py
lcs/agents/racs/components/__init__.py
lcs/agents/racs/components/alp.py
lcs/agents/racs/components/genetic_algorithm.py
lcs/representations/RealValueEncoder.py
lcs/representations/UBR.py
lcs/representations/__init__.py
lcs/representations/visualization.py
lcs/strategies/__init__.py
lcs/strategies/action_selection.py
lcs/strategies/anticipatory_learning_process.py
lcs/strategies/genetic_algorithms.py
pyalcs.egg-info/PKG-INFO
pyalcs.egg-info/SOURCES.txt
pyalcs.egg-info/dependency_links.txt
pyalcs.egg-info/not-zip-safe
pyalcs.egg-info/top_level.txt
